Metadata-Version: 1.1
Name: automated
Version: 1.1.4
Summary: A automated package
Home-page: https://github.com/gabrielfern/automated-leda-tasks
Author: Gabriel Fernandes
Author-email: gabrielfernndss@gmail.com
License: MIT
Platform: UNKNOWN
Classifier: Programming Language :: Python :: 2
Classifier: Programming Language :: Python :: 3
